paranoid_zookeeper/__init__.py
paranoid_zookeeper/artifact.py
paranoid_zookeeper/checkinresult.py
paranoid_zookeeper/httphealthcheck.py
paranoid_zookeeper/zookeeper.py
paranoid_zookeeper/zookeeperservicecontext.py
paranoid_zookeeper-2.0.0.dist-info/LICENSE.md
paranoid_zookeeper-2.0.0.dist-info/METADATA
paranoid_zookeeper-2.0.0.dist-info/WHEEL
paranoid_zookeeper-2.0.0.dist-info/top_level.txt
paranoid_zookeeper-2.0.0.dist-info/RECORD
