Metadata-Version: 2.1
Name: paranoid-zookeeper
Version: 2.0.0
Summary: Python Paranoid Zookeeper SDK
Home-page: https://paranoid.software
Author: Paranoid Software
Author-email: info@paranoid.software
License: MIT
Classifier: Programming Language :: Python :: 3
Classifier: Operating System :: OS Independent
Requires-Python: >=3.6
License-File: LICENSE.md
Requires-Dist: requests
